graph_cli/__init__.py
graph_cli/graph.py
graph_cli/main.py
graph_cli/options.py
graph_cli-0.1.19.dist-info/LICENSE
graph_cli-0.1.19.dist-info/METADATA
graph_cli-0.1.19.dist-info/WHEEL
graph_cli-0.1.19.dist-info/entry_points.txt
graph_cli-0.1.19.dist-info/top_level.txt
graph_cli-0.1.19.dist-info/RECORD
