Metadata-Version: 2.1
Name: graph-cli
Version: 0.1.19
Summary: A CLI utility to create graphs from CSV files.
Home-page: https://github.com/mcastorina/graph-cli
Author: miccah
Author-email: m.castorina93@gmail.com
Classifier: Programming Language :: Python :: 2.7
Classifier: Programming Language :: Python :: 3
Classifier: License :: OSI Approved :: GNU General Public License v3 (GPLv3)
Classifier: Operating System :: OS Independent
License-File: LICENSE
Requires-Dist: numpy
Requires-Dist: pandas
Requires-Dist: matplotlib
